MANIFEST.in
README.rst
setup.cfg
setup.py
authentication/__init__.py
authentication/admin.py
authentication/apps.py
authentication/helper.py
authentication/models.py
authentication/tests.py
authentication/urls.py
authentication/views.py
authentication/migrations/0001_initial.py
authentication/migrations/0002_forgotpassword.py
authentication/migrations/__init__.py
authentication/templates/authentication/base.html
authentication/templates/authentication/forgot_password.html
authentication/templates/authentication/invalid.html
authentication/templates/authentication/login.html
authentication/templates/authentication/newverify.html
authentication/templates/authentication/register.html
authentication/templates/authentication/reset_password.html
authentication/templates/authentication/success.html
django_authsimple.egg-info/PKG-INFO
django_authsimple.egg-info/SOURCES.txt
django_authsimple.egg-info/dependency_links.txt
django_authsimple.egg-info/requires.txt
django_authsimple.egg-info/top_level.txt